{
  "release": {
    "description": "Releases",
    "hide": false,
    "last_updated": "2024-02-27T22:32:59.000Z",
    "last_updated_url": "https://github.com/hotio/jackett/actions/runs/8072102500",
    "latest": true,
    "tags": [
      "release",
      "release-0.21.1861",
      "release-99382d5"
    ]
  },
  "testing": {
    "description": "Pre-releases",
    "hide": false,
    "last_updated": "2024-02-27T22:33:06.000Z",
    "last_updated_url": "https://github.com/hotio/jackett/actions/runs/8072103108",
    "latest": false,
    "tags": [
      "testing",
      "testing-0.21.1861",
      "testing-b5491a5"
    ]
  }
}
